{
  "profile": {
    "uuid": "7c8f564d-3ee8-5f4d-ae66-88bbdc21657d",
    "metadata": {
      "title": "TX-RAMP Level 1 (Rev4 baseline)",
      "last-modified": "2026-06-10T00:00:00Z",
      "version": "1.0.0",
      "oscal-version": "1.2.2"
    },
    "imports": [
      {
        "href": "../catalogs/NIST_SP-800-53_rev4_catalog.json",
        "include-controls": [
          {
            "with-ids": [
              "ac-1",
              "ac-14",
              "ac-17",
              "ac-18",
              "ac-19",
              "ac-2",
              "ac-20",
              "ac-22",
              "ac-3",
              "ac-7",
              "ac-8",
              "at-1",
              "at-2",
              "at-3",
              "at-4",
              "au-1",
              "au-11",
              "au-12",
              "au-2",
              "au-3",
              "au-4",
              "au-5",
              "au-6",
              "au-8",
              "au-9",
              "ca-1",
              "ca-2",
              "ca-2.1",
              "ca-3",
              "ca-5",
              "ca-6",
              "ca-7",
              "ca-9",
              "cm-1",
              "cm-10",
              "cm-11",
              "cm-2",
              "cm-4",
              "cm-6",
              "cm-7",
              "cm-8",
              "cp-1",
              "cp-10",
              "cp-2",
              "cp-3",
              "cp-4",
              "cp-9",
              "ia-1",
              "ia-2",
              "ia-2.1",
              "ia-2.12",
              "ia-4",
              "ia-5",
              "ia-5.1",
              "ia-5.11",
              "ia-6",
              "ia-7",
              "ia-8",
              "ia-8.2",
              "ia-8.3",
              "ir-1",
              "ir-2",
              "ir-4",
              "ir-5",
              "ir-6",
              "ir-7",
              "ir-8",
              "ir-9",
              "ma-1",
              "ma-2",
              "ma-4",
              "ma-5",
              "mp-1",
              "mp-2",
              "mp-6",
              "mp-7",
              "pe-1",
              "pe-13",
              "pe-14",
              "pe-15",
              "pe-16",
              "pe-2",
              "pe-3",
              "pe-6",
              "pe-8",
              "pl-1",
              "pl-2",
              "pl-4",
              "ps-1",
              "ps-2",
              "ps-3",
              "ps-4",
              "ps-5",
              "ps-6",
              "ps-7",
              "ps-8",
              "ra-1",
              "ra-2",
              "ra-3",
              "ra-5",
              "sa-1",
              "sa-2",
              "sa-3",
              "sa-4",
              "sa-4.1",
              "sa-5",
              "sa-9",
              "sc-1",
              "sc-15",
              "sc-20",
              "sc-21",
              "sc-22",
              "sc-39",
              "sc-5",
              "sc-7",
              "si-1",
              "si-12",
              "si-16",
              "si-2",
              "si-3",
              "si-4",
              "si-5"
            ]
          }
        ]
      }
    ],
    "merge": {
      "as-is": true
    }
  }
}
